{
  "kpis": [
    {
      "id": "adoption-percentage",
      "name": "Adoption Percentage",
      "description": "Overall AI adoption rate across the organization",
      "currentValue": 68.5,
      "targetValue": 85.0,
      "scale": {
        "min": 1,
        "max": 100,
        "unit": "%"
      },
      "trend": "up",
      "category": "Adoption",
      "subMetrics": [
        {
          "id": "active-users",
          "name": "Active Users",
          "description": "Number of active users utilizing AI tools",
          "currentValue": 342,
          "targetValue": 500,
          "scale": {
            "min": 0,
            "max": 1000,
            "unit": "users"
          },
          "trend": "up"
        },
        {
          "id": "committed-lines-percentage",
          "name": "Committed Lines of Code",
          "description": "Percentage of committed lines of code generated by AI out of total",
          "currentValue": 45.2,
          "targetValue": 70.0,
          "scale": {
            "min": 0,
            "max": 100,
            "unit": "%"
          },
          "trend": "up"
        }
      ]
    },
    {
      "id": "roi",
      "name": "Velocity and Quality",
      "description": "Velocity and Quality metrics for AI initiatives",
      "currentValue": 3.2,
      "targetValue": 5.0,
      "scale": {
        "min": 0,
        "max": 10,
        "unit": "x"
      },
      "trend": "up",
      "category": "Financial",
      "subMetrics": [
        {
          "id": "cycle-time",
          "name": "Cycle Time",
          "description": "Average development cycle time",
          "currentValue": 12.5,
          "targetValue": 8.0,
          "scale": {
            "min": 0,
            "max": 30,
            "unit": "days"
          },
          "trend": "down"
        },
        {
          "id": "quality-index",
          "name": "Quality Index",
          "description": "Overall quality score for AI-generated outputs",
          "currentValue": 78.5,
          "targetValue": 90.0,
          "scale": {
            "min": 1,
            "max": 100,
            "unit": "%"
          },
          "trend": "up"
        }
      ]
    },
    {
      "id": "dev-experience",
      "name": "Dev Experience",
      "description": "Developer experience score for AI tools and workflows",
      "currentValue": 3.2,
      "targetValue": 5.0,
      "scale": {
        "min": 1,
        "max": 5,
        "unit": "score"
      },
      "trend": "up",
      "category": "Quality"
    },
    {
      "id": "cost",
      "name": "Cost",
      "description": "Financial cost metrics for AI initiatives",
      "currentValue": 0,
      "targetValue": 0,
      "scale": {
        "min": 0,
        "max": 100,
        "unit": "%"
      },
      "trend": "down",
      "category": "Financial",
      "subMetrics": [
        {
          "id": "estimation-trend",
          "name": "Estimation Trend",
          "description": "Trend in cost estimation accuracy",
          "currentValue": 75.0,
          "targetValue": 90.0,
          "scale": {
            "min": 0,
            "max": 100,
            "unit": "%"
          },
          "trend": "up"
        },
        {
          "id": "revenue-per-employee",
          "name": "Overall Revenue per Employee",
          "description": "Total revenue generated per employee",
          "currentValue": 125000,
          "targetValue": 150000,
          "scale": {
            "min": 0,
            "max": 200000,
            "unit": "$"
          },
          "trend": "up"
        }
      ]
    }
  ]
}
